argformat/__init__.py
argformat/ansi.py
argformat/markdown.py
lscolors-1.0.3.dist-info/METADATA
lscolors-1.0.3.dist-info/WHEEL
lscolors-1.0.3.dist-info/entry_points.txt
lscolors-1.0.3.dist-info/licenses/LICENSE
lscolors/__init__.py
lscolors/__main__.py
lscolors/cli.py
lscolors/cmd.py
lscolors/commands/__init__.py
lscolors/commands/chart.py
lscolors/commands/check.py
lscolors/commands/configs.py
lscolors/commands/docs.py
lscolors/commands/paint.py
lscolors/commands/report.py
lscolors/commands/samples.py
lscolors/commands/sort.py
lscolors/commands/utils/__init__.py
lscolors/commands/utils/colors.py
lscolors/commands/utils/config.py
lscolors/commands/utils/mkdir.py
lscolors/sample-configs/.dircolors
lscolors/sample-configs/.lscolors.yml
lscolors-1.0.3.dist-info/RECORD
