Metadata-Version: 2.1
Name: lscolors
Version: 1.0.3
Summary: dircolors utilities
Keywords: dircolors,xterm-256color,color-scheme,terminal,shell,ls,tree
Author-Email: Russel Lane <russel@rlane.com>
License: MIT
Classifier: Development Status :: 4 - Beta
Classifier: Intended Audience :: End Users/Desktop
Classifier: License :: OSI Approved :: MIT License
Classifier: Programming Language :: Python :: 3
Classifier: Topic :: System :: Console Fonts
Classifier: Topic :: System :: Filesystems
Classifier: Topic :: System :: Shells
Classifier: Topic :: Terminals
Classifier: Topic :: Utilities
Project-URL: Homepage, https://github.com/russellane/lscolors
Requires-Python: >=3.10
Requires-Dist: ansicolors>=1.1.8
Requires-Dist: pyyaml>=6.0.2
Requires-Dist: rlane-libcli>=1.0.8
